pants_basedpyright/__init__.py
pants_basedpyright/basedpyright.lock
pants_basedpyright/fieldset.py
pants_basedpyright/partition.py
pants_basedpyright/register.py
pants_basedpyright/request.py
pants_basedpyright/rules.py
pants_basedpyright/skip_field.py
pants_basedpyright/subsystem.py
pants_basedpyright/tests/__init__.py
pants_basedpyright/tests/conftest.py
pants_basedpyright/tests/rule_integration_test.py
pants_basedpyright-0.3.0.dist-info/METADATA
pants_basedpyright-0.3.0.dist-info/WHEEL
pants_basedpyright-0.3.0.dist-info/licenses/LICENSE
pants_basedpyright-0.3.0.dist-info/RECORD
