Metadata-Version: 2.4
Name: pants-basedpyright
Version: 0.3.0
Summary: Pantsbuild plugin for basedpyright type checking
Project-URL: Homepage, https://github.com/jacoblearned/pants-basedpyright
Project-URL: Documentation, https://github.com/jacoblearned/pants-basedpyright
Project-URL: Repository, https://github.com/jacoblearned/pants-basedpyright
Project-URL: Issues, https://github.com/jacoblearned/pants-basedpyright/issues
Project-URL: Changelog, https://github.com/jacoblearned/pants-basedpyright/blob/main/CHANGELOG.md
Author: Jacob Learned
License-Expression: MIT
License-File: LICENSE
Keywords: basedpyright,monorepo,pants,pantsbuild,type checking
Requires-Python: >=3.11
